zscli/__init__.py
zscli/cli.py
zscli/version.py
zscli/zscli.py
zscli-0.1.0.dist-info/entry_points.txt
zscli-0.1.0.dist-info/LICENSE
zscli-0.1.0.dist-info/WHEEL
zscli-0.1.0.dist-info/METADATA
zscli-0.1.0.dist-info/RECORD
