Metadata-Version: 2.1
Name: zscli
Version: 0.1.0
Summary: Top-level package for zscli.
Keywords: zscli
Author-email: Matt Krueger <mkrueger@rstms.net>
Classifier: Intended Audience :: Developers
Classifier: Natural Language :: English
Classifier: Programming Language :: Python :: 3
Classifier: Programming Language :: Python :: 3.8
Classifier: Programming Language :: Python :: 3.9
Classifier: Programming Language :: Python :: 3.10
Requires-Dist: click==8.0.3
Requires-Dist: requests==2.27.1
Requires-Dist: black==22.1.0 ; extra == "dev"
Requires-Dist: bump2version==1.0.1 ; extra == "dev"
Requires-Dist: coverage==6.3.1 ; extra == "dev"
Requires-Dist: flake8==4.0.1 ; extra == "dev"
Requires-Dist: pytest==7.0.0 ; extra == "dev"
Requires-Dist: pytest-datadir==1.3.1 ; extra == "dev"
Requires-Dist: tox==3.24.5 ; extra == "dev"
Requires-Dist: Sphinx==4.4.0 ; extra == "docs"
Requires-Dist: sphinx-click==3.1.0 ; extra == "docs"
Project-URL: Home, https://github.com/rstms/zscli
Provides-Extra: dev
Provides-Extra: docs
